Training_Mgmt/__init__.py
Training_Mgmt/start.py
Training_Mgmt/Exercise/Exercise.py
Training_Mgmt/Exercise/Record.py
Training_Mgmt/Exercise/__init__.py
Training_Mgmt/Person/Person.py
Training_Mgmt/Person/__init__.py
Training_Mgmt/Person/calculate.py
Training_Mgmt/Person/record.py
Training_Mgmt-0.0.2.dist-info/LICENSE.txt
Training_Mgmt-0.0.2.dist-info/METADATA
Training_Mgmt-0.0.2.dist-info/WHEEL
Training_Mgmt-0.0.2.dist-info/top_level.txt
Training_Mgmt-0.0.2.dist-info/RECORD
