Metadata-Version: 2.1
Name: Training-Mgmt
Version: 0.0.2
Summary: Nutrition and exercise managment software
Author-email: "Xing (Will) Xu" <willxu2023@outlook.com>, "Bingshen (Gevin) Yang" <bi2@ualberta.ca>
Project-URL: Homepage, https://github.com/willgeminix/Training_Mgmt.git
Classifier: Programming Language :: Python :: 3
Classifier: License :: OSI Approved :: MIT License
Classifier: Operating System :: OS Independent
Requires-Python: >=3.9
License-File: LICENSE.txt
